odoo/addons/stock_picking_force_assign/README.rst
odoo/addons/stock_picking_force_assign/__init__.py
odoo/addons/stock_picking_force_assign/__manifest__.py
odoo/addons/stock_picking_force_assign/data/ir_config_parameter.xml
odoo/addons/stock_picking_force_assign/demo/res_groups.xml
odoo/addons/stock_picking_force_assign/i18n/stock_picking_force_assign.pot
odoo/addons/stock_picking_force_assign/models/__init__.py
odoo/addons/stock_picking_force_assign/models/stock_picking.py
odoo/addons/stock_picking_force_assign/readme/CONFIGURE.rst
odoo/addons/stock_picking_force_assign/readme/CONTRIBUTORS.rst
odoo/addons/stock_picking_force_assign/readme/DESCRIPTION.rst
odoo/addons/stock_picking_force_assign/readme/USAGE.rst
odoo/addons/stock_picking_force_assign/security/stock_picking_force_assign_security.xml
odoo/addons/stock_picking_force_assign/static/description/icon.png
odoo/addons/stock_picking_force_assign/static/description/index.html
odoo/addons/stock_picking_force_assign/tests/__init__.py
odoo/addons/stock_picking_force_assign/tests/test_stock_picking_force_assign.py
odoo/addons/stock_picking_force_assign/views/stock_picking.xml
odoo12_addon_stock_picking_force_assign-12.0.1.1.0.dist-info/METADATA
odoo12_addon_stock_picking_force_assign-12.0.1.1.0.dist-info/WHEEL
odoo12_addon_stock_picking_force_assign-12.0.1.1.0.dist-info/top_level.txt
odoo12_addon_stock_picking_force_assign-12.0.1.1.0.dist-info/RECORD
